datameta/__init__.py
datameta/errors.py
datameta/linting.py
datameta/pshell.py
datameta/resource.py
datameta/routes.py
datameta/samplesheet.py
datameta/settings.py
datameta/siteid.py
datameta/storage.py
datameta/utils.py
datameta/validation.py
datameta/alembic/script.py.mako
datameta/alembic/versions/README.txt
datameta/api/__init__.py
datameta/api/apikeys.py
datameta/api/appsettings.py
datameta/api/download.py
datameta/api/files.py
datameta/api/groups.py
datameta/api/metadata.py
datameta/api/metadatasets.py
datameta/api/openapi.yaml
datameta/api/password.py
datameta/api/register.py
datameta/api/server.py
datameta/api/services.py
datameta/api/submissions.py
datameta/api/totp_secret.py
datameta/api/upload.py
datameta/api/users.py
datameta/api/ui/__init__.py
datameta/api/ui/admin.py
datameta/api/ui/convert.py
datameta/api/ui/forgot.py
datameta/api/ui/pending.py
datameta/api/ui/view.py
datameta/defaults/appsettings.yaml
datameta/email/__init__.py
datameta/email/smtp.py
datameta/models/__init__.py
datameta/models/db.py
datameta/models/meta.py
datameta/scripts/__init__.py
datameta/scripts/initialize_db.py
datameta/security/__init__.py
datameta/security/authz.py
datameta/security/tfaz.py
datameta/security/tokenz.py
datameta/static/pyramid-16x16.png
datameta/static/pyramid.png
datameta/static/theme.css
datameta/static/css/dataTables.bootstrap5.css
datameta/static/css/datameta.css
datameta/static/css/fileupload.css
datameta/static/js/account.js
datameta/static/js/admin.js
datameta/static/js/dataTables.bootstrap5.min.js
datameta/static/js/datameta.js
datameta/static/js/fileupload.js
datameta/static/js/forgot.js
datameta/static/js/jquery.dataTables.min.js
datameta/static/js/register.js
datameta/static/js/setpass.js
datameta/static/js/settfa.js
datameta/static/js/submit.js
datameta/static/js/view.js
datameta/templates/404.pt
datameta/templates/account.pt
datameta/templates/admin.pt
datameta/templates/forgot.pt
datameta/templates/home.pt
datameta/templates/layout-minimal.pt
datameta-1.1.1.dist-info/LICENSE.txt
datameta-1.1.1.dist-info/METADATA
datameta-1.1.1.dist-info/WHEEL
datameta-1.1.1.dist-info/entry_points.txt
datameta-1.1.1.dist-info/top_level.txt
datameta-1.1.1.dist-info/RECORD
