Metadata-Version: 2.1
Name: datameta
Version: 1.1.1
Summary: DataMeta - submission server for data and associated metadata
Home-page: 
Author: Leon Kuchenbecker
Author-email: leon.kuchenbecker@uni-tuebingen.de
License: Apache 2.0
Keywords: web pyramid pylons
Classifier: Programming Language :: Python
Classifier: License :: OSI Approved :: Apache Software License
Classifier: Framework :: Pyramid
Classifier: Topic :: Internet :: WWW/HTTP
Classifier: Topic :: Internet :: WWW/HTTP :: WSGI :: Application
License-File: LICENSE.txt
Requires-Dist: bcrypt
Requires-Dist: psycopg2
Requires-Dist: plaster-pastedeploy
Requires-Dist: pandas (>=1.2.2)
Requires-Dist: openpyxl
Requires-Dist: xlrd (>=1.0.0)
Requires-Dist: pyramid
Requires-Dist: pyramid-chameleon
Requires-Dist: pyramid-beaker (==0.8)
Requires-Dist: pylibmc (==1.6.1)
Requires-Dist: pyramid-debugtoolbar
Requires-Dist: waitress
Requires-Dist: alembic
Requires-Dist: pyramid-retry
Requires-Dist: pyramid-tm
Requires-Dist: SQLAlchemy (==1.3.*)
Requires-Dist: transaction
Requires-Dist: zope.sqlalchemy
Requires-Dist: pyramid-openapi3 (==0.11)
Requires-Dist: jsonschema (<4)
Requires-Dist: openapi-core (<0.14)
Requires-Dist: openapi-schema-validator (==0.1.5)
Requires-Dist: openapi-spec-validator (==0.3.1)
Requires-Dist: pytest (>=3.7.4)
Requires-Dist: dataclasses-json (==0.5.2)
Requires-Dist: pyyaml
Requires-Dist: python-json-logger
Requires-Dist: gunicorn (==20.0.4)
Requires-Dist: pyotp
Requires-Dist: cryptography
Requires-Dist: qrcode[pil]
Provides-Extra: testing
Requires-Dist: WebTest (>=1.3.1) ; extra == 'testing'
Requires-Dist: pytest-cov ; extra == 'testing'
Requires-Dist: sqlalchemy-utils ; extra == 'testing'
Requires-Dist: requests ; extra == 'testing'
Requires-Dist: parameterized (>=0.8.1) ; extra == 'testing'
Requires-Dist: mypy ; extra == 'testing'
